jupytery_admin/__init__.py
jupytery_admin/__main__.py
jupytery_admin/application.py
jupytery_admin/handlers.py
jupytery_admin/hubextension/__init__.py
jupytery_admin/hubextension/app.py
jupytery_admin/hubextension/data_files.py
jupytery_admin/hubextension/main.py
jupytery_admin/hubextension/version.py
jupytery_admin/static/favicon.ico
jupytery_admin/templates/error.html
jupytery_admin/templates/page.html
jupytery_admin-0.0.5.dist-info/LICENSE
jupytery_admin-0.0.5.dist-info/METADATA
jupytery_admin-0.0.5.dist-info/WHEEL
jupytery_admin-0.0.5.dist-info/entry_points.txt
jupytery_admin-0.0.5.dist-info/top_level.txt
jupytery_admin-0.0.5.dist-info/RECORD
