Metadata-Version: 2.1
Name: jupytery-admin
Version: 0.0.5
Summary: Jupyter Admin
Home-page: UNKNOWN
License: UNKNOWN
Platform: UNKNOWN
Requires-Python: >=3.8
License-File: LICENSE
Requires-Dist: alembic
Requires-Dist: jupyter-server
Requires-Dist: jupyterhub (>=1.4.1)
Requires-Dist: pluggy
Requires-Dist: tornado (>=6.0.4)
Requires-Dist: traitlets
Requires-Dist: jinja2
Provides-Extra: test
Requires-Dist: pytest ; extra == 'test'
